{"title":"`init.el`","markdown":{"headingText":"`init.el`","containsRefs":false,"markdown":"\nThis is init.el configuration for Emacs on MacOS using Org-roam.\n\nWe can save this directly as `~/.emacs.d/init.el` file.\n\n\n```default\n;;;;;;;;;;;;;;;;;;;;;;;;\n;; Emacs init.el\n;; Platform: MacOSX\n;; Author: Moinul Islam\n;;;;;;;;;;;;;;;;;;;;;;;\n\n;; -----------------------------------------------\n;; Package Manager Setup (package.el + use-package)\n;; -----------------------------------------------\n(require 'package)\n(setq package-archives\n       '((\"melpa\"       . \"https://melpa.org/packages/\")\n        (\"melpa-stable\" . \"https://stable.melpa.org/packages/\")\n        (\"gnu\"          . \"https://elpa.gnu.org/packages/\")\n        (\"nongnu\"       . \"https://elpa.nongnu.org/nongnu/\")\n        (\"org\"          . \"https://orgmode.org/elpa/\")))\n(package-initialize)\n(unless package-archive-contents\n  (package-refresh-contents))\n\n(unless (package-installed-p 'use-package)\n  (package-install 'use-package))\n(eval-when-compile\n  (require 'use-package))\n(setq use-package-always-ensure t)\n\n;; -----------------------------------\n;; Save customization to separate file\n;; -----------------------------------\n(setq custom-file (expand-file-name \"custom.el\" user-emacs-directory))\n(load custom-file 'noerror)\n\n;; ----------------------------------------\n;; Enable Mac-specific Environment Settings\n;; ----------------------------------------\n\n;; Let init-macos.el to work\n;;(load (expand-file-name \"init-macos.el\" user-emacs-directory))\n\n;; -----------------\n;; Visual Appearance\n;; -----------------\n;;(set-face-attribute 'default nil :font \"Monaco-17\")\n(use-package doom-themes\n  :ensure t\n  :config\n  (load-theme 'doom-one t))\n\n;;(set-face-attribute 'default nil :font \"Monaco-17\")\n;; HiDPI-aware dynamic font setup (GUI) + fallback (TTY)\n(defun my/setup-font-based-on-resolution ()\n  \"Adjust font size automatically based on display resolution, with terminal fallback.\"\n  (interactive)\n  (if (display-graphic-p)\n      (let* ((display-width (display-pixel-width))\n             (font-profiles '((3000 . (:font \"Monaco\" :size 200))\n                              (2500 . (:font \"Monaco\" :size 190))\n                              (1920 . (:font \"Monaco\" :size 180))\n                              (0    . (:font \"Monaco\" :size 170))))\n             (selected-profile\n              (cl-loop for (min-width . settings) in font-profiles\n                       when (> display-width min-width)\n                       return settings)))\n        (when selected-profile\n          (let ((font-name (plist-get selected-profile :font))\n                (font-size (plist-get selected-profile :size)))\n            (set-face-attribute 'default nil :font font-name :height font-size)\n            (message \"GUI: Font set to %s (%d)\" font-name font-size))))\n    ;; fallback for terminal mode\n    (set-face-attribute 'default nil :height 130)\n    (message \"TTY: Default font height set to 130\")))\n\n;; Apply after GUI is ready\n(add-hook 'window-setup-hook #'my/setup-font-based-on-resolution)\n\n(global-display-line-numbers-mode 1)\n(global-visual-line-mode 1)\n\n;; ----------------------------\n;; General Editing Enhancements\n;; ----------------------------\n(use-package smex\n  :bind (\"M-x\" . smex))\n\n(use-package smartparens\n  :config\n  (smartparens-global-mode t)\n  (show-smartparens-global-mode t)\n  (sp-pair \"\\\\[\" \"\\\\]\"))\n\n(use-package rainbow-delimiters\n  :hook (prog-mode . rainbow-delimiters-mode))\n\n(use-package rainbow-identifiers\n  :hook ((prog-mode latex-mode LaTeX-mode) . rainbow-identifiers-mode))\n\n(use-package adaptive-wrap\n  :hook (visual-line-mode . adaptive-wrap-prefix-mode)\n  :config\n  (setq-default adaptive-wrap-extra-indent 0))\n\n(use-package visual-fill-column\n  :config\n  (setq-default fill-column 99999))\n\n;; -------------------------------\n;; 🔤 Spell Checking & Dictionary\n;; -------------------------------\n(setq ispell-program-name \"aspell\") \n(setq ispell-dictionary \"en\")       ;; default dictionary\n\n;; Enable Flyspell in text and org modes\n(dolist (hook '(text-mode-hook org-mode-hook))\n  (add-hook hook 'flyspell-mode))\n\n;; Optional: enable in comments for code\n(add-hook 'prog-mode-hook 'flyspell-prog-mode)\n\n;; Set correction keybinding (use M-$ to check word)\n(global-set-key (kbd \"C-;\") 'flyspell-correct-wrapper)\n\n(use-package flyspell\n  :ensure t\n  :hook ((text-mode . flyspell-mode)\n         (org-mode  . flyspell-mode)\n         (prog-mode . flyspell-prog-mode))\n  :config\n  (setq ispell-program-name \"aspell\"\n        ispell-dictionary \"en\"))\n\n(use-package flyspell-correct\n  :ensure t\n  :after flyspell\n  :bind (:map flyspell-mode-map\n              (\"C-;\" . flyspell-correct-wrapper)))\n\n;; ---------------------\n;; 📒 Org Mode Enhancements\n;; ---------------------\n(use-package org\n  :ensure t\n  :hook ((org-mode . org-indent-mode)\n         (org-mode . visual-line-mode))\n  :config\n  (setq org-log-done 'time                          ; Log time when TODOs are marked done\n        org-startup-folded t                        ; Start with sections folded\n        org-icalendar-include-todo t                ; Include TODOs in iCalendar export\n        org-hide-emphasis-markers t                 ; Hide *bold*, /italic/, etc.\n        org-pretty-entities t                       ; Show LaTeX-like entities as UTF symbols\n        org-return-follows-link t))                 ; Enter follows links\n\n;; -----------------\n;; 🧠 Org-roam Setup\n;; -----------------\n(use-package org-roam\n  :ensure t\n  :init\n  (setq org-roam-v2-ack t)\n  :custom\n  (org-roam-directory (file-truename \"~/Dropbox/org/roam/\"))\n  (org-roam-dailies-directory \"daily/\")\n  (org-roam-completion-everywhere t)\n  (org-roam-capture-templates\n   '((\"d\" \"default\" plain\n      \"%?\"\n      :target (file+head \"%<%Y%m%d%H%M%S>-${slug}.org\"\n                         \"#+title: ${title}\\n#+date: %U\\n\")\n      :unnarrowed t)))\n  (org-roam-dailies-capture-templates\n   '((\"d\" \"daily\" entry\n      \"* %?\"\n      :target (file+head \"%<%Y-%m-%d>.org\"\n                         \"#+title: %<%Y-%m-%d>\\n#+date: %U\\n\\n\"))))\n  :bind ((\"C-c n l\" . org-roam-buffer-toggle)\n         (\"C-c n f\" . org-roam-node-find)\n         (\"C-c n i\" . org-roam-node-insert)\n         (\"C-c n d\" . org-roam-dailies-capture-today)\n         (\"C-c n t\" . org-roam-dailies-goto-today))\n  :config\n  (org-roam-db-autosync-enable))\n\n;; -------------------------------------------\n;; LaTeX / AUCTeX + latexmk on MacOSX\n;; -------------------------------------------\n\n(use-package tex\n  :ensure auctex\n  :defer t\n  :hook (LaTeX-mode . my/latex-setup)\n  :config\n  (setq TeX-auto-save t\n        TeX-parse-self t\n        TeX-save-query nil\n        TeX-PDF-mode t\n        TeX-source-correlate-mode t\n        TeX-source-correlate-method 'synctex)\n\n  ;; Set default viewer to Skim or Preview.app\n  (setq TeX-view-program-selection\n        '(((output-pdf \"PDF Viewer\"))))\n\n  ;; Skim version (with SyncTeX)\n  ;; You can switch \"PDF Viewer\" below to \"Preview.app\" if you prefer\n  (setq TeX-view-program-list\n        '((\"PDF Viewer\" \"/Applications/Skim.app/Contents/SharedSupport/displayline -b -g %n %o %b\")))\n\n  ;; Preview.app version — open default Preview.app instead:\n  ;; (setq TeX-view-program-list\n  ;;       '((\"PDF Viewer\" \"open -a Preview.app %o\")))\n\n  ;; Add latexmk command\n  (add-to-list 'TeX-command-list\n               '(\"LatexMk\"\n                 \"latexmk -pdf -synctex=1 -interaction=nonstopmode %s\"\n                 TeX-run-TeX nil t\n                 :help \"Run latexmk for PDF output\"))\n\n  ;; Make latexmk the default compile command\n  (setq TeX-command-default \"LatexMk\"))\n\n(defun my/latex-setup ()\n  \"My custom LaTeX setup.\"\n  (turn-on-reftex)\n  (setq reftex-plug-into-AUCTeX t)\n  (flyspell-mode 1)\n  (LaTeX-math-mode 1)\n  (visual-line-mode 1))\n\n;; ---------------------------\n;; Company-mode\n;; ---------------------------\n(use-package company\n  :hook ((after-init . global-company-mode)\n         (LaTeX-mode . company-mode))\n  :config\n  (setq company-idle-delay 0.2\n        company-minimum-prefix-length 2\n        company-tooltip-align-annotations t\n        company-dabbrev-downcase nil))\n\n;; Auto-save\n(setq auto-save-visited-file-name t\n      auto-save-interval 100\n      auto-save-timeout 5)\n\n;; ----------------------\n;; Handy Custom Shortcuts\n;; ----------------------\n(setq debug-on-error t)\n(electric-indent-mode -1)\n\n;; Save current word to kill ring\n(global-set-key (kbd \"C-x w\")\n  (lambda ()\n    (interactive)\n    (save-excursion\n      (forward-char)\n      (backward-sexp)\n      (let ((pos (point)))\n        (forward-sexp)\n        (kill-ring-save pos (point))))))\n\n(provide 'init)\n```\n\n","srcMarkdownNoYaml":""},"formats":{"html":{"identifier":{"display-name":"HTML","target-format":"html","base-format":"html"},"execute":{"fig-width":7,"fig-height":5,"fig-format":"retina","fig-dpi":96,"df-print":"default","error":false,"eval":true,"cache":null,"freeze":false,"echo":true,"output":true,"warning":true,"include":true,"keep-md":false,"keep-ipynb":false,"ipynb":null,"enabled":null,"daemon":null,"daemon-restart":false,"debug":false,"ipynb-filters":[],"ipynb-shell-interactivity":null,"plotly-connected":true,"engine":"markdown"},"render":{"keep-tex":false,"keep-typ":false,"keep-source":false,"keep-hidden":false,"prefer-html":false,"output-divs":true,"output-ext":"html","fig-align":"default","fig-pos":null,"fig-env":null,"code-fold":"none","code-overflow":"scroll","code-link":false,"code-line-numbers":false,"code-tools":false,"tbl-colwidths":"auto","merge-includes":true,"inline-includes":false,"preserve-yaml":false,"latex-auto-mk":true,"latex-auto-install":true,"latex-clean":true,"latex-min-runs":1,"latex-max-runs":10,"latex-makeindex":"makeindex","latex-makeindex-opts":[],"latex-tlmgr-opts":[],"latex-input-paths":[],"latex-output-dir":null,"link-external-icon":false,"link-external-newwindow":false,"self-contained-math":false,"format-resources":[],"notebook-links":true},"pandoc":{"standalone":true,"wrap":"none","default-image-extension":"png","to":"html","output-file":"ch_1.html"},"language":{"toc-title-document":"Table of contents","toc-title-website":"On this page","related-formats-title":"Other Formats","related-notebooks-title":"Notebooks","source-notebooks-prefix":"Source","other-links-title":"Other Links","code-links-title":"Code Links","launch-dev-container-title":"Launch Dev Container","launch-binder-title":"Launch Binder","article-notebook-label":"Article Notebook","notebook-preview-download":"Download Notebook","notebook-preview-download-src":"Download Source","notebook-preview-back":"Back to Article","manuscript-meca-bundle":"MECA Bundle","section-title-abstract":"Abstract","section-title-appendices":"Appendices","section-title-footnotes":"Footnotes","section-title-references":"References","section-title-reuse":"Reuse","section-title-copyright":"Copyright","section-title-citation":"Citation","appendix-attribution-cite-as":"For attribution, please cite this work as:","appendix-attribution-bibtex":"BibTeX citation:","appendix-view-license":"View License","title-block-author-single":"Author","title-block-author-plural":"Authors","title-block-affiliation-single":"Affiliation","title-block-affiliation-plural":"Affiliations","title-block-published":"Published","title-block-modified":"Modified","title-block-keywords":"Keywords","callout-tip-title":"Tip","callout-note-title":"Note","callout-warning-title":"Warning","callout-important-title":"Important","callout-caution-title":"Caution","code-summary":"Code","code-tools-menu-caption":"Code","code-tools-show-all-code":"Show All Code","code-tools-hide-all-code":"Hide All Code","code-tools-view-source":"View Source","code-tools-source-code":"Source Code","tools-share":"Share","tools-download":"Download","code-line":"Line","code-lines":"Lines","copy-button-tooltip":"Copy to Clipboard","copy-button-tooltip-success":"Copied!","repo-action-links-edit":"Edit this page","repo-action-links-source":"View source","repo-action-links-issue":"Report an issue","back-to-top":"Back to top","search-no-results-text":"No results","search-matching-documents-text":"matching documents","search-copy-link-title":"Copy link to search","search-hide-matches-text":"Hide additional matches","search-more-match-text":"more match in this document","search-more-matches-text":"more matches in this document","search-clear-button-title":"Clear","search-text-placeholder":"","search-detached-cancel-button-title":"Cancel","search-submit-button-title":"Submit","search-label":"Search","toggle-section":"Toggle section","toggle-sidebar":"Toggle sidebar navigation","toggle-dark-mode":"Toggle dark mode","toggle-reader-mode":"Toggle reader mode","toggle-navigation":"Toggle navigation","crossref-fig-title":"Figure","crossref-tbl-title":"Table","crossref-lst-title":"Listing","crossref-thm-title":"Theorem","crossref-lem-title":"Lemma","crossref-cor-title":"Corollary","crossref-prp-title":"Proposition","crossref-cnj-title":"Conjecture","crossref-def-title":"Definition","crossref-exm-title":"Example","crossref-exr-title":"Exercise","crossref-ch-prefix":"Chapter","crossref-apx-prefix":"Appendix","crossref-sec-prefix":"Section","crossref-eq-prefix":"Equation","crossref-lof-title":"List of Figures","crossref-lot-title":"List of Tables","crossref-lol-title":"List of Listings","environment-proof-title":"Proof","environment-remark-title":"Remark","environment-solution-title":"Solution","listing-page-order-by":"Order By","listing-page-order-by-default":"Default","listing-page-order-by-date-asc":"Oldest","listing-page-order-by-date-desc":"Newest","listing-page-order-by-number-desc":"High to Low","listing-page-order-by-number-asc":"Low to High","listing-page-field-date":"Date","listing-page-field-title":"Title","listing-page-field-description":"Description","listing-page-field-author":"Author","listing-page-field-filename":"File Name","listing-page-field-filemodified":"Modified","listing-page-field-subtitle":"Subtitle","listing-page-field-readingtime":"Reading Time","listing-page-field-wordcount":"Word Count","listing-page-field-categories":"Categories","listing-page-minutes-compact":"{0} min","listing-page-category-all":"All","listing-page-no-matches":"No matching items","listing-page-words":"{0} words","listing-page-filter":"Filter","draft":"Draft"},"metadata":{"lang":"en","fig-responsive":true,"quarto-version":"1.6.40","bibliography":["references.bib"],"editor":"visual","theme":["darkly","brand"]},"extensions":{"book":{"multiFile":true}}},"pdf":{"identifier":{"display-name":"PDF","target-format":"pdf","base-format":"pdf"},"execute":{"fig-width":5.5,"fig-height":3.5,"fig-format":"pdf","fig-dpi":300,"df-print":"default","error":false,"eval":true,"cache":null,"freeze":false,"echo":true,"output":true,"warning":true,"include":true,"keep-md":false,"keep-ipynb":false,"ipynb":null,"enabled":null,"daemon":null,"daemon-restart":false,"debug":false,"ipynb-filters":[],"ipynb-shell-interactivity":null,"plotly-connected":true,"engine":"markdown"},"render":{"keep-tex":false,"keep-typ":false,"keep-source":false,"keep-hidden":false,"prefer-html":false,"output-divs":true,"output-ext":"pdf","fig-align":"default","fig-pos":null,"fig-env":null,"code-fold":"none","code-overflow":"scroll","code-link":false,"code-line-numbers":false,"code-tools":false,"tbl-colwidths":true,"merge-includes":true,"inline-includes":false,"preserve-yaml":false,"latex-auto-mk":true,"latex-auto-install":true,"latex-clean":true,"latex-min-runs":1,"latex-max-runs":10,"latex-makeindex":"makeindex","latex-makeindex-opts":[],"latex-tlmgr-opts":[],"latex-input-paths":[],"latex-output-dir":null,"link-external-icon":false,"link-external-newwindow":false,"self-contained-math":false,"format-resources":[]},"pandoc":{"pdf-engine":"xelatex","standalone":true,"variables":{"graphics":true,"tables":true},"default-image-extension":"pdf","to":"pdf","output-file":"ch_1.pdf"},"language":{"toc-title-document":"Table of contents","toc-title-website":"On this page","related-formats-title":"Other Formats","related-notebooks-title":"Notebooks","source-notebooks-prefix":"Source","other-links-title":"Other Links","code-links-title":"Code Links","launch-dev-container-title":"Launch Dev Container","launch-binder-title":"Launch Binder","article-notebook-label":"Article Notebook","notebook-preview-download":"Download Notebook","notebook-preview-download-src":"Download Source","notebook-preview-back":"Back to Article","manuscript-meca-bundle":"MECA Bundle","section-title-abstract":"Abstract","section-title-appendices":"Appendices","section-title-footnotes":"Footnotes","section-title-references":"References","section-title-reuse":"Reuse","section-title-copyright":"Copyright","section-title-citation":"Citation","appendix-attribution-cite-as":"For attribution, please cite this work as:","appendix-attribution-bibtex":"BibTeX citation:","appendix-view-license":"View License","title-block-author-single":"Author","title-block-author-plural":"Authors","title-block-affiliation-single":"Affiliation","title-block-affiliation-plural":"Affiliations","title-block-published":"Published","title-block-modified":"Modified","title-block-keywords":"Keywords","callout-tip-title":"Tip","callout-note-title":"Note","callout-warning-title":"Warning","callout-important-title":"Important","callout-caution-title":"Caution","code-summary":"Code","code-tools-menu-caption":"Code","code-tools-show-all-code":"Show All Code","code-tools-hide-all-code":"Hide All Code","code-tools-view-source":"View Source","code-tools-source-code":"Source Code","tools-share":"Share","tools-download":"Download","code-line":"Line","code-lines":"Lines","copy-button-tooltip":"Copy to Clipboard","copy-button-tooltip-success":"Copied!","repo-action-links-edit":"Edit this page","repo-action-links-source":"View source","repo-action-links-issue":"Report an issue","back-to-top":"Back to top","search-no-results-text":"No results","search-matching-documents-text":"matching documents","search-copy-link-title":"Copy link to search","search-hide-matches-text":"Hide additional matches","search-more-match-text":"more match in this document","search-more-matches-text":"more matches in this document","search-clear-button-title":"Clear","search-text-placeholder":"","search-detached-cancel-button-title":"Cancel","search-submit-button-title":"Submit","search-label":"Search","toggle-section":"Toggle section","toggle-sidebar":"Toggle sidebar navigation","toggle-dark-mode":"Toggle dark mode","toggle-reader-mode":"Toggle reader mode","toggle-navigation":"Toggle navigation","crossref-fig-title":"Figure","crossref-tbl-title":"Table","crossref-lst-title":"Listing","crossref-thm-title":"Theorem","crossref-lem-title":"Lemma","crossref-cor-title":"Corollary","crossref-prp-title":"Proposition","crossref-cnj-title":"Conjecture","crossref-def-title":"Definition","crossref-exm-title":"Example","crossref-exr-title":"Exercise","crossref-ch-prefix":"Chapter","crossref-apx-prefix":"Appendix","crossref-sec-prefix":"Section","crossref-eq-prefix":"Equation","crossref-lof-title":"List of Figures","crossref-lot-title":"List of Tables","crossref-lol-title":"List of Listings","environment-proof-title":"Proof","environment-remark-title":"Remark","environment-solution-title":"Solution","listing-page-order-by":"Order By","listing-page-order-by-default":"Default","listing-page-order-by-date-asc":"Oldest","listing-page-order-by-date-desc":"Newest","listing-page-order-by-number-desc":"High to Low","listing-page-order-by-number-asc":"Low to High","listing-page-field-date":"Date","listing-page-field-title":"Title","listing-page-field-description":"Description","listing-page-field-author":"Author","listing-page-field-filename":"File Name","listing-page-field-filemodified":"Modified","listing-page-field-subtitle":"Subtitle","listing-page-field-readingtime":"Reading Time","listing-page-field-wordcount":"Word Count","listing-page-field-categories":"Categories","listing-page-minutes-compact":"{0} min","listing-page-category-all":"All","listing-page-no-matches":"No matching items","listing-page-words":"{0} words","listing-page-filter":"Filter","draft":"Draft"},"metadata":{"block-headings":true,"bibliography":["references.bib"],"editor":"visual","documentclass":"scrreprt"},"extensions":{"book":{"selfContainedOutput":true}}}},"projectFormats":["html","pdf"]}